online-svr/__init__.py
online-svr/core.py
online-svr/test.py
online-svr/utils.py
online_svr/__init__.py
online_svr/core.py
online_svr/test.py
online_svr/utils.py
online_svr-0.1.2.dist-info/LICENSE
online_svr-0.1.2.dist-info/METADATA
online_svr-0.1.2.dist-info/WHEEL
online_svr-0.1.2.dist-info/top_level.txt
online_svr-0.1.2.dist-info/RECORD
