Metadata-Version: 2.1
Name: online-svr
Version: 0.1.2
Summary: Uma biblioteca para realizar previsões em SVR com aprendizado online
Home-page: https://github.com/ademirNeto/online-svr
Author: Ademir Neto
Author-email: ademir.bsn@gmail.com
Classifier: Programming Language :: Python :: 3
Classifier: License :: OSI Approved :: MIT License
Classifier: Operating System :: OS Independent
Requires-Python: >=3.9
License-File: LICENSE
Requires-Dist: numpy
Requires-Dist: pandas
Requires-Dist: scikit-learn
Requires-Dist: statsmodels
Requires-Dist: scipy
